sbi/__init__.py
sbi/__version__.py
sbi/sbi_types.py
sbi/analysis/__init__.py
sbi/analysis/conditional_density.py
sbi/analysis/plot.py
sbi/analysis/sensitivity_analysis.py
sbi/analysis/tensorboard_output.py
sbi/diagnostics/__init__.py
sbi/diagnostics/lc2st.py
sbi/diagnostics/misspecification.py
sbi/diagnostics/sbc.py
sbi/diagnostics/tarp.py
sbi/examples/__init__.py
sbi/examples/minimal.py
sbi/inference/__init__.py
sbi/inference/abc/__init__.py
sbi/inference/abc/abc_base.py
sbi/inference/abc/mcabc.py
sbi/inference/abc/smcabc.py
sbi/inference/posteriors/__init__.py
sbi/inference/posteriors/base_posterior.py
sbi/inference/posteriors/direct_posterior.py
sbi/inference/posteriors/ensemble_posterior.py
sbi/inference/posteriors/importance_posterior.py
sbi/inference/posteriors/mcmc_posterior.py
sbi/inference/posteriors/posterior_parameters.py
sbi/inference/posteriors/rejection_posterior.py
sbi/inference/posteriors/vector_field_posterior.py
sbi/inference/posteriors/vi_posterior.py
sbi/inference/potentials/__init__.py
sbi/inference/potentials/base_potential.py
sbi/inference/potentials/likelihood_based_potential.py
sbi/inference/potentials/posterior_based_potential.py
sbi/inference/potentials/ratio_based_potential.py
sbi/inference/potentials/score_fn_iid.py
sbi/inference/potentials/vector_field_potential.py
sbi/inference/snle/__init__.py
sbi/inference/snpe/__init__.py
sbi/inference/snre/__init__.py
sbi/inference/trainers/__init__.py
sbi/inference/trainers/base.py
sbi/inference/trainers/marginal/__init__.py
sbi/inference/trainers/marginal/marginal_base.py
sbi/inference/trainers/nle/__init__.py
sbi/inference/trainers/nle/mnle.py
sbi/inference/trainers/nle/nle_a.py
sbi/inference/trainers/nle/nle_base.py
sbi/inference/trainers/npe/__init__.py
sbi/inference/trainers/npe/mnpe.py
sbi/inference/trainers/npe/npe_a.py
sbi/inference/trainers/npe/npe_b.py
sbi/inference/trainers/npe/npe_base.py
sbi/inference/trainers/npe/npe_c.py
sbi/inference/trainers/nre/__init__.py
sbi-0.25.0.dist-info/licenses/LICENSE.txt
sbi-0.25.0.dist-info/METADATA
sbi-0.25.0.dist-info/WHEEL
sbi-0.25.0.dist-info/top_level.txt
sbi-0.25.0.dist-info/RECORD
