Metadata-Version: 2.4
Name: sbi
Version: 0.25.0
Summary: Simulation-based inference.
Author-email: sbi-dev <simulation.based.inference@gmail.com>
Project-URL: documentation, https://sbi-dev.github.io/sbi/
Project-URL: source, https://github.com/sbi-dev/sbi
Project-URL: tracker, https://github.com/sbi-dev/sbi/issues
Keywords: Bayesian inference,simulation-based inference,PyTorch
Classifier: Intended Audience :: Developers
Classifier: Intended Audience :: Education
Classifier: Intended Audience :: Science/Research
Classifier: Topic :: Adaptive Technologies
Classifier: Topic :: Scientific/Engineering
Classifier: Topic :: Scientific/Engineering :: Artificial Intelligence
Classifier: Topic :: Scientific/Engineering :: Mathematics
Classifier: License :: OSI Approved :: Apache Software License
Classifier: Natural Language :: English
Classifier: Operating System :: OS Independent
Classifier: Programming Language :: Python :: 3
Classifier: Development Status :: 3 - Alpha
Requires-Python: >=3.10
License-File: LICENSE.txt
Requires-Dist: arviz
Requires-Dist: joblib>=1.0.0
Requires-Dist: matplotlib
Requires-Dist: notebook<=6.4.12
Requires-Dist: numpy
Requires-Dist: pillow
Requires-Dist: pyknos>=0.16.0
Requires-Dist: pyro-ppl>=1.3.1
Requires-Dist: scikit-learn
Requires-Dist: scipy
Requires-Dist: tensorboard
Requires-Dist: torch<2.6.0,>=1.13.0
Requires-Dist: tqdm
Requires-Dist: pymc>=5.0.0
Requires-Dist: zuko>=1.2.0
Provides-Extra: doc
Requires-Dist: ipython<=8.9.0; extra == "doc"
Requires-Dist: jupyter_contrib_nbextensions; extra == "doc"
Requires-Dist: mike; extra == "doc"
Requires-Dist: mkdocs; extra == "doc"
Requires-Dist: markdown-include; extra == "doc"
Requires-Dist: mkdocs-material; extra == "doc"
Requires-Dist: mkdocs-redirects; extra == "doc"
Requires-Dist: mkdocstrings[python]>=0.18; extra == "doc"
Requires-Dist: nbconvert; extra == "doc"
Requires-Dist: nbformat; extra == "doc"
Requires-Dist: traitlets<=5.9.0; extra == "doc"
Requires-Dist: sphinx; extra == "doc"
Requires-Dist: sphinx-autobuild; extra == "doc"
Requires-Dist: sphinx_autodoc_typehints; extra == "doc"
Requires-Dist: sphinx-math-dollar; extra == "doc"
Requires-Dist: sphinx-design; extra == "doc"
Requires-Dist: myst-nb; extra == "doc"
Requires-Dist: jupytext; extra == "doc"
Requires-Dist: sphinx-book-theme; extra == "doc"
Provides-Extra: dev
Requires-Dist: ffmpeg; extra == "dev"
Requires-Dist: pre-commit==4.0.1; extra == "dev"
Requires-Dist: pyyaml; extra == "dev"
Requires-Dist: pyright; extra == "dev"
Requires-Dist: ruff==0.9.0; extra == "dev"
Requires-Dist: pytest; extra == "dev"
Requires-Dist: pytest-cov; extra == "dev"
Requires-Dist: pytest-testmon; extra == "dev"
Requires-Dist: pytest-xdist; extra == "dev"
Requires-Dist: pytest-harvest; extra == "dev"
Requires-Dist: pytest-split; extra == "dev"
Requires-Dist: torchtestcase; extra == "dev"
Dynamic: license-file
